{
  "stage_a_changes": 105,
  "stage_b_replacements": [
    [
      "עקומול",
      "אקמול",
      8
    ],
    [
      "העתק עדבק",
      "העתק הדבק",
      8
    ],
    [
      "במקריב",
      "בערב",
      8
    ],
    [
      "עקומול",
      "אקמול",
      9
    ],
    [
      "כהי מים",
      "כולי מים",
      10
    ],
    [
      "עזות",
      "הזעות",
      13
    ],
    [
      "עזות",
      "הזעות",
      14
    ],
    [
      "עזות",
      "הזעות",
      15
    ],
    [
      "הסמינים",
      "הסימפטומים",
      19
    ],
    [
      "מייחה",
      "ליחה",
      20
    ],
    [
      "תחילות",
      "בחילות",
      23
    ],
    [
      "יציאה תקינות",
      "יציאות תקינות",
      25
    ],
    [
      "הרמונית",
      "ערמונית",
      39
    ],
    [
      "הרמונית",
      "ערמונית",
      40
    ],
    [
      "הרמונית",
      "ערמונית",
      42
    ],
    [
      "בליסה",
      "בלעיסה",
      47
    ],
    [
      "מהעצם",
      "ממח העצם",
      70
    ],
    [
      "מערך העצם",
      "מח העצם",
      77
    ],
    [
      "פרוטיק",
      "פרטי",
      79
    ],
    [
      "פרוטיק",
      "פרטי",
      80
    ],
    [
      "שאירו",
      "שלנו",
      81
    ],
    [
      "מהעצם",
      "ממח העצם",
      86
    ],
    [
      "מהעצם",
      "ממח העצם",
      88
    ],
    [
      "רגישה יותר בנוח",
      "מרגישה יותר בנוח",
      88
    ],
    [
      "קרדיולוק",
      "קרדילול",
      96
    ],
    [
      "קרדיולוק",
      "קרדילול",
      99
    ],
    [
      "חטפם",
      "התקף",
      110
    ],
    [
      "חומס",
      "חום",
      117
    ],
    [
      "לדיין",
      "לדון",
      117
    ],
    [
      "המסתרמות",
      "המסתמיות",
      119
    ],
    [
      "מולטאק",
      "Multaq",
      119
    ]
  ],
  "stage_c_duplicates_removed": 1,
  "stage_c_duplicate_lines": [
    36
  ],
  "stage_d_corrections": [],
  "stage_e_warnings": [
    "New medical terms introduced (possible hallucination): {'Multaq', 'קרדילול'}"
  ],
  "validation_passed": true,
  "numbers_before_count": 8,
  "numbers_after_count": 8,
  "medical_terms_before": [
    "ראומטולוגים",
    "מסתמים",
    "TEE",
    "אנדוקרדיטיס",
    "קרדיולוגים",
    "Ultrasound",
    "פירפור",
    "PET",
    "IgG4",
    "סטרואידים",
    "פרוקור",
    "דיגוקסין",
    "המטולוגים",
    "DVT",
    "אשפוז",
    "גרנולומות",
    "טמפורלית",
    "אימורן",
    "PET-CT",
    "סרקואיד",
    "ביופסיה",
    "CT",
    "לימפומה"
  ],
  "medical_terms_after": [
    "קרדילול",
    "ראומטולוגים",
    "מסתמים",
    "TEE",
    "אנדוקרדיטיס",
    "קרדיולוגים",
    "Ultrasound",
    "פירפור",
    "PET",
    "IgG4",
    "סטרואידים",
    "פרוקור",
    "דיגוקסין",
    "המטולוגים",
    "DVT",
    "אשפוז",
    "גרנולומות",
    "טמפורלית",
    "אימורן",
    "Multaq",
    "PET-CT",
    "סרקואיד",
    "ביופסיה",
    "CT",
    "לימפומה"
  ]
}